factoriolib/__init__.py
factoriolib/_decorators.py
factoriolib/blueprints.py
factoriolib/core.py
factoriolib/entities.py
factoriolib/instruments.py
factoriolib/items.py
factoriolib/strings.py
factoriolib/tiles.py
factoriolib/utility.py
factoriolib-0.0.2.dist-info/LICENSE
factoriolib-0.0.2.dist-info/METADATA
factoriolib-0.0.2.dist-info/WHEEL
factoriolib-0.0.2.dist-info/top_level.txt
factoriolib-0.0.2.dist-info/RECORD
