Metadata-Version: 2.1
Name: factoriolib
Version: 0.0.2
Summary: A small package to manipulate factorio blueprints
Home-page: https://gitlab.com/justin-guth.de/factoriolib
Author: justin-guth.de
Author-email: factoriolib@justin-guth.de
License: UNKNOWN
Project-URL: Bug Tracker, https://gitlab.com/justin-guth.de/factoriolib/-/issues
Platform: UNKNOWN
Classifier: Programming Language :: Python :: 3
Classifier: License :: OSI Approved :: GNU General Public License v3 (GPLv3)
Classifier: Operating System :: OS Independent
Requires-Python: >=3.6
License-File: LICENSE
